{
  "station_id": 10813,
  "station_detail": {
    "station_id": 10813,
    "station_name": "PADGA",
    "latitude": 19.3569,
    "longitude": 73.1566,
    "address": "THANE, Thane, Maharashtra, 421362, India",
    "area": "THANE",
    "navigation_link": "https://www.google.com/maps/search/?api=1&query=19.3569,73.1566",
    "closing_status": {
      "text": "Open Now",
      "text_color": "#12D377"
    },
    "total_distance": "8252 kms",
    "operational_time": "24 hours",
    "connector_types": [
      {
        "id": 1,
        "connector_name": "CCS-2",
        "connector_image_url": "https://d3orevttu06iqr.cloudfront.net/connector_images/ccs-2.png"
      }
    ],
    "avg_review_rating": 4.4,
    "no_of_reviews": 5,
    "station_image_url": "https://statiq-images-prod.s3.ap-south-1.amazonaws.com/charging-stations-images/default-charging-station.jpg",
    "is_connected": false,
    "station_banner": "https://d3orevttu06iqr.cloudfront.net/banner/bpcl+banner.png",
    "landmark": null,
    "amenities_icon": [],
    "plugin_details": [
      {
        "charger_id": 60741,
        "price_with_currency": "₹ 14.0",
        "price": 14.0,
        "currency": "INR",
        "symbol": "₹",
        "connectors": [
          {
            "display_id": 1,
            "connector_id": 22066,
            "connector_type": "CCS-2",
            "connector_image": "https://d3orevttu06iqr.cloudfront.net/connector_images/ccs-2.png",
            "availability": false,
            "error_message": "Disconnected",
            "connector_type_id": 1,
            "connector_status": "charging"
          },
          {
            "display_id": 2,
            "connector_id": 22067,
            "connector_type": "CCS-2",
            "connector_image": "https://d3orevttu06iqr.cloudfront.net/connector_images/ccs-2.png",
            "availability": false,
            "error_message": "Disconnected",
            "connector_type_id": 1,
            "connector_status": "available"
          }
        ],
        "type": "DC",
        "power_rating": 120.0,
        "charger_name": "PADGA",
        "last_used_on": "20/05/2026"
      }
    ],
    "review_stats": {
      "percentage_per_star": {
        "1": 0,
        "2": 0,
        "3": 20,
        "4": 20,
        "5": 60
      }
    },
    "map_pin_url": "https://statiq-images-prod.s3.ap-south-1.amazonaws.com/charging-pin/Captive.png",
    "steps_to_reach": false,
    "station_city_name": "Thane",
    "station_access_type": "public",
    "availability": "Unavailable",
    "highest_power_rating": 120.0,
    "charger_type_of_station": "DC",
    "station_images": []
  },
  "nearby_stations": [
    {
      "id": 10813,
      "station_name": "PADGA",
      "latitude": 19.3569,
      "longitude": 73.1566,
      "address": "THANE, Thane, Maharashtra, 421362, India",
      "area": "THANE",
      "avg_review_rating": 4.4,
      "navigation_link": "https://www.google.com/maps/search/?api=1&query=19.3569,73.1566",
      "is_connected": false,
      "station_type": [
        {
          "type": "DC",
          "bg_color": "#F4F4F7",
          "text_color": "#101941"
        }
      ],
      "access_type": 1,
      "is_community_listed": false,
      "branding_logo": "https://d3orevttu06iqr.cloudfront.net/charging-pin/unavailable.png"
    },
    {
      "id": 7351,
      "station_name": "2000290-DASMESH ENTERPRISE",
      "latitude": 19.345342,
      "longitude": 73.136575,
      "address": "TAL-BHIVANDI, Achalpur, Maharashtra, 421302, India",
      "area": "TAL-BHIVANDI",
      "avg_review_rating": 0.0,
      "navigation_link": "https://www.google.com/maps/search/?api=1&query=19.345342,73.136575",
      "is_connected": false,
      "station_type": [
        {
          "type": "DC",
          "bg_color": "#F4F4F7",
          "text_color": "#101941"
        }
      ],
      "access_type": 1,
      "is_community_listed": false,
      "branding_logo": "https://d3orevttu06iqr.cloudfront.net/charging-pin/unavailable.png"
    },
    {
      "id": 8412,
      "station_name": "C. R. CONTRACTOR",
      "latitude": 19.344343,
      "longitude": 73.127291,
      "address": "NH3 VADAPE, THANE, Thane, Maharashtra, 421302, India",
      "area": "NH3 VADAPE, THANE",
      "avg_review_rating": 4.49,
      "navigation_link": "https://www.google.com/maps/search/?api=1&query=19.344343,73.127291",
      "is_connected": true,
      "station_type": [
        {
          "type": "DC",
          "bg_color": "#F4F4F7",
          "text_color": "#101941"
        }
      ],
      "access_type": 1,
      "is_community_listed": false,
      "branding_logo": "https://d3orevttu06iqr.cloudfront.net/charging-pin/BPCL+-+default.png"
    },
    {
      "id": 8397,
      "station_name": "SHRADDHA PETROLEUM",
      "latitude": 19.3769,
      "longitude": 73.2068,
      "address": "AT.PO.DHOHALE VILLAGE NH3 ,  NEAR WALYA DHABA  THANE, Thane, Maharashtra, 421101, India",
      "area": "AT.PO.DHOHALE VILLAGE NH3 ,  NEAR WALYA DHABA  THANE",
      "avg_review_rating": 0.0,
      "navigation_link": "https://www.google.com/maps/search/?api=1&query=19.3769,73.2068",
      "is_connected": true,
      "station_type": [
        {
          "type": "DC",
          "bg_color": "#F4F4F7",
          "text_color": "#101941"
        }
      ],
      "access_type": 1,
      "is_community_listed": false,
      "branding_logo": "https://d3orevttu06iqr.cloudfront.net/charging-pin/BPCL+-+default.png"
    },
    {
      "id": 8395,
      "station_name": "SUMANGAL PETROLEUM",
      "latitude": 19.398371,
      "longitude": 73.240797,
      "address": "RO AT KASANE, ON NH3, Thane, Maharashtra, 421601, India",
      "area": "RO AT KASANE, ON NH3",
      "avg_review_rating": 4.62,
      "navigation_link": "https://www.google.com/maps/search/?api=1&query=19.398371,73.240797",
      "is_connected": true,
      "station_type": [
        {
          "type": "DC",
          "bg_color": "#F4F4F7",
          "text_color": "#101941"
        }
      ],
      "access_type": 1,
      "is_community_listed": false,
      "branding_logo": "https://d3orevttu06iqr.cloudfront.net/charging-pin/BPCL+-+default.png"
    }
  ],
  "ac_count": 0,
  "dc_count": 1,
  "ac_prices": [],
  "dc_prices": [
    14.0
  ],
  "scraped_at": "2026-05-21T08:09:09.186135+00:00",
  "parse_success": true,
  "missing_fields": [
    "landmark",
    "amenities_icon"
  ],
  "coverage_pct": 90.9
}