{
  "station_id": 14362,
  "station_detail": {
    "station_id": 14362,
    "station_name": "2012418 - MANOJ FUELS",
    "latitude": 24.395935,
    "longitude": 81.840658,
    "address": "M.P. Sidhi Byohari Road, Panwar, Sangram Opposite, Sidhi, Madhya Pradesh, 486661, India",
    "area": "M.P. Sidhi Byohari Road, Panwar, Sangram Opposite",
    "navigation_link": "https://www.google.com/maps/search/?api=1&query=24.395935,81.840658",
    "closing_status": {
      "text": "Open Now",
      "text_color": "#12D377"
    },
    "total_distance": "9192 kms",
    "operational_time": "24 hours",
    "connector_types": [
      {
        "id": 1,
        "connector_name": "CCS-2",
        "connector_image_url": "https://d3orevttu06iqr.cloudfront.net/connector_images/ccs-2.png"
      }
    ],
    "avg_review_rating": 4.3,
    "no_of_reviews": 20,
    "station_image_url": "https://statiq-images-prod.s3.ap-south-1.amazonaws.com/charging-stations-images/default-charging-station.jpg",
    "is_connected": false,
    "station_banner": "https://d3orevttu06iqr.cloudfront.net/banner/bpcl+banner.png",
    "landmark": null,
    "amenities_icon": [],
    "plugin_details": [
      {
        "charger_id": 66325,
        "price_with_currency": "₹ 14.0",
        "price": 14.0,
        "currency": "INR",
        "symbol": "₹",
        "connectors": [
          {
            "display_id": 1,
            "connector_id": 30595,
            "connector_type": "CCS-2",
            "connector_image": "https://d3orevttu06iqr.cloudfront.net/connector_images/ccs-2.png",
            "availability": false,
            "error_message": "Disconnected",
            "connector_type_id": 1,
            "connector_status": "available"
          },
          {
            "display_id": 2,
            "connector_id": 30596,
            "connector_type": "CCS-2",
            "connector_image": "https://d3orevttu06iqr.cloudfront.net/connector_images/ccs-2.png",
            "availability": false,
            "error_message": "Disconnected",
            "connector_type_id": 1,
            "connector_status": "available"
          }
        ],
        "type": "DC",
        "power_rating": 120.0,
        "charger_name": "2012418 - MANOJ FUELS",
        "last_used_on": "14/03/2026"
      }
    ],
    "review_stats": {
      "percentage_per_star": {
        "1": 5,
        "2": 0,
        "3": 10,
        "4": 30,
        "5": 55
      }
    },
    "map_pin_url": "https://statiq-images-prod.s3.ap-south-1.amazonaws.com/charging-pin/Captive.png",
    "steps_to_reach": false,
    "station_city_name": "Sidhi",
    "station_access_type": "public",
    "availability": "Unavailable",
    "highest_power_rating": 120.0,
    "charger_type_of_station": "DC",
    "station_images": []
  },
  "nearby_stations": [
    {
      "id": 14362,
      "station_name": "2012418 - MANOJ FUELS",
      "latitude": 24.395935,
      "longitude": 81.840658,
      "address": "M.P. Sidhi Byohari Road, Panwar, Sangram Opposite, Sidhi, Madhya Pradesh, 486661, India",
      "area": "M.P. Sidhi Byohari Road, Panwar, Sangram Opposite",
      "avg_review_rating": 4.3,
      "navigation_link": "https://www.google.com/maps/search/?api=1&query=24.395935,81.840658",
      "is_connected": false,
      "station_type": [
        {
          "type": "DC",
          "bg_color": "#F4F4F7",
          "text_color": "#101941"
        }
      ],
      "access_type": 1,
      "is_community_listed": false,
      "branding_logo": "https://d3orevttu06iqr.cloudfront.net/charging-pin/unavailable.png"
    },
    {
      "id": 12213,
      "station_name": "2013609 - JARHA FILLING STATION",
      "latitude": 24.642855,
      "longitude": 81.528547,
      "address": "AAMBI MANGAWAN, Rewa, Madhya Pradesh, 486111, India",
      "area": "AAMBI MANGAWAN",
      "avg_review_rating": 4.54,
      "navigation_link": "https://www.google.com/maps/search/?api=1&query=24.642855,81.528547",
      "is_connected": false,
      "station_type": [
        {
          "type": "DC",
          "bg_color": "#F4F4F7",
          "text_color": "#101941"
        }
      ],
      "access_type": 1,
      "is_community_listed": false,
      "branding_logo": "https://d3orevttu06iqr.cloudfront.net/charging-pin/unavailable.png"
    },
    {
      "id": 12209,
      "station_name": "AASTHA FUELS",
      "latitude": 24.56646,
      "longitude": 81.414561,
      "address": "RAMNAI NH7, TEHSIL - RAIPURKARCHULIYAN, Rewa, Madhya Pradesh, 486001, India",
      "area": "RAMNAI NH7, TEHSIL - RAIPURKARCHULIYAN",
      "avg_review_rating": 3.89,
      "navigation_link": "https://www.google.com/maps/search/?api=1&query=24.56646,81.414561",
      "is_connected": true,
      "station_type": [
        {
          "type": "DC",
          "bg_color": "#F4F4F7",
          "text_color": "#101941"
        }
      ],
      "access_type": 1,
      "is_community_listed": false,
      "branding_logo": "https://d3orevttu06iqr.cloudfront.net/charging-pin/BPCL+-+default.png"
    },
    {
      "id": 12214,
      "station_name": "2013610 - SHEFALI FILLING STATION",
      "latitude": 24.557759,
      "longitude": 81.37997,
      "address": "Chorgadi, Rewa, Madhya Pradesh, 486001, India",
      "area": "Chorgadi",
      "avg_review_rating": 4.49,
      "navigation_link": "https://www.google.com/maps/search/?api=1&query=24.557759,81.37997",
      "is_connected": false,
      "station_type": [
        {
          "type": "DC",
          "bg_color": "#F4F4F7",
          "text_color": "#101941"
        }
      ],
      "access_type": 1,
      "is_community_listed": false,
      "branding_logo": "https://d3orevttu06iqr.cloudfront.net/charging-pin/unavailable.png"
    },
    {
      "id": 11900,
      "station_name": "2012014 - RAJENDRAA PETROLEUM",
      "latitude": 24.561902,
      "longitude": 81.342347,
      "address": "Anantpur, ON NH 7 BYPASS, Bypass, Rewa, Madhya Pradesh, 486001, India",
      "area": "Anantpur, ON NH 7 BYPASS, Bypass",
      "avg_review_rating": 4.68,
      "navigation_link": "https://www.google.com/maps/search/?api=1&query=24.561902,81.342347",
      "is_connected": false,
      "station_type": [
        {
          "type": "DC",
          "bg_color": "#F4F4F7",
          "text_color": "#101941"
        }
      ],
      "access_type": 1,
      "is_community_listed": false,
      "branding_logo": "https://d3orevttu06iqr.cloudfront.net/charging-pin/unavailable.png"
    }
  ],
  "ac_count": 0,
  "dc_count": 1,
  "ac_prices": [],
  "dc_prices": [
    14.0
  ],
  "scraped_at": "2026-05-21T08:13:37.563325+00:00",
  "parse_success": true,
  "missing_fields": [
    "landmark",
    "amenities_icon"
  ],
  "coverage_pct": 90.9
}