{
  "station_id": 6791,
  "station_detail": {
    "station_id": 6791,
    "station_name": "Tatya Petroleum",
    "latitude": 18.832306,
    "longitude": 75.55096,
    "address": "KRANTI NAGAR, PATODA, PATODA BUS STAND ROAD, DISTRICT - BEED, Beed, Maharashtra, 414204, India",
    "area": "KRANTI NAGAR, PATODA, PATODA BUS STAND ROAD, DISTRICT - BEED",
    "navigation_link": "https://www.google.com/maps/search/?api=1&query=18.832306,75.55096",
    "closing_status": {
      "text": "Open Now",
      "text_color": "#12D377"
    },
    "total_distance": "8498 kms",
    "operational_time": "24 hours",
    "connector_types": [
      {
        "id": 5,
        "connector_name": "Wall",
        "connector_image_url": "https://d3orevttu06iqr.cloudfront.net/connector_images/type-1.png"
      }
    ],
    "avg_review_rating": 5.0,
    "no_of_reviews": 2,
    "station_image_url": "https://statiq-images-prod.s3.ap-south-1.amazonaws.com/charging-stations-images/default-charging-station.jpg",
    "is_connected": false,
    "station_banner": "https://d3orevttu06iqr.cloudfront.net/banner/bpcl+banner.png",
    "landmark": null,
    "amenities_icon": [],
    "plugin_details": [
      {
        "charger_id": 54377,
        "price_with_currency": "₹ 14.0",
        "price": 14.0,
        "currency": "INR",
        "symbol": "₹",
        "connectors": [
          {
            "display_id": 1,
            "connector_id": 12576,
            "connector_type": "Wall",
            "connector_image": "https://d3orevttu06iqr.cloudfront.net/connector_images/type-1.png",
            "availability": false,
            "error_message": "Disconnected",
            "connector_type_id": 5,
            "connector_status": "faulted"
          }
        ],
        "type": "AC",
        "power_rating": 3.0,
        "charger_name": "Tatya Petroleum  EV - AC",
        "last_used_on": "26/07/2024"
      }
    ],
    "review_stats": {
      "percentage_per_star": {
        "1": 0,
        "2": 0,
        "3": 0,
        "4": 0,
        "5": 100
      }
    },
    "map_pin_url": "https://statiq-images-prod.s3.ap-south-1.amazonaws.com/charging-pin/Captive.png",
    "steps_to_reach": false,
    "station_city_name": "Beed",
    "station_access_type": "public",
    "availability": "Unavailable",
    "highest_power_rating": 3.0,
    "charger_type_of_station": "AC",
    "station_images": []
  },
  "nearby_stations": [
    {
      "id": 6791,
      "station_name": "Tatya Petroleum",
      "latitude": 18.832306,
      "longitude": 75.55096,
      "address": "KRANTI NAGAR, PATODA, PATODA BUS STAND ROAD, DISTRICT - BEED, Beed, Maharashtra, 414204, India",
      "area": "KRANTI NAGAR, PATODA, PATODA BUS STAND ROAD, DISTRICT - BEED",
      "avg_review_rating": 0.0,
      "navigation_link": "https://www.google.com/maps/search/?api=1&query=18.832306,75.55096",
      "is_connected": false,
      "station_type": [
        {
          "type": "AC",
          "bg_color": "#F4F4F7",
          "text_color": "#101941"
        }
      ],
      "access_type": 1,
      "is_community_listed": false,
      "branding_logo": "https://d3orevttu06iqr.cloudfront.net/charging-pin/unavailable.png"
    },
    {
      "id": 6905,
      "station_name": "2012601-M KHAN PETROLEUM",
      "latitude": 18.832833,
      "longitude": 75.718806,
      "address": "BHARAT PETROLEUM CORPN. LTD,  SASEWADI,PATODA MANJARSUMBA RAOD, Ahmednagar, Maharashtra, 431125, India",
      "area": "BHARAT PETROLEUM CORPN. LTD,  SASEWADI,PATODA MANJARSUMBA RAOD",
      "avg_review_rating": 4.67,
      "navigation_link": "https://www.google.com/maps/search/?api=1&query=18.832833,75.718806",
      "is_connected": false,
      "station_type": [
        {
          "type": "DC",
          "bg_color": "#F4F4F7",
          "text_color": "#101941"
        }
      ],
      "access_type": 1,
      "is_community_listed": false,
      "branding_logo": "https://d3orevttu06iqr.cloudfront.net/charging-pin/unavailable.png"
    },
    {
      "id": 15241,
      "station_name": "LG MISAL",
      "latitude": 18.935969,
      "longitude": 75.336472,
      "address": "SURVEY NO 46 4A, AHMEDNAGAR-BEED RD, AMALNER,BEED, Ahmadnagar, Maharashtra, 413207, India",
      "area": "SURVEY NO 46 4A, AHMEDNAGAR-BEED RD, AMALNER,BEED",
      "avg_review_rating": 0.0,
      "navigation_link": "https://www.google.com/maps/search/?api=1&query=18.935969,75.336472",
      "is_connected": false,
      "station_type": [
        {
          "type": "DC",
          "bg_color": "#F4F4F7",
          "text_color": "#101941"
        }
      ],
      "access_type": 1,
      "is_community_listed": false,
      "branding_logo": "https://d3orevttu06iqr.cloudfront.net/charging-pin/unavailable.png"
    },
    {
      "id": 6904,
      "station_name": "2000918-HINA ROCK DRILLS",
      "latitude": 18.978183,
      "longitude": 75.764055,
      "address": "Beed, Ahmednagar, Maharashtra, 431122, India",
      "area": "Beed",
      "avg_review_rating": 4.67,
      "navigation_link": "https://www.google.com/maps/search/?api=1&query=18.978183,75.764055",
      "is_connected": false,
      "station_type": [
        {
          "type": "DC",
          "bg_color": "#F4F4F7",
          "text_color": "#101941"
        }
      ],
      "access_type": 1,
      "is_community_listed": false,
      "branding_logo": "https://d3orevttu06iqr.cloudfront.net/charging-pin/unavailable.png"
    },
    {
      "id": 11040,
      "station_name": "BAFNA PVC",
      "latitude": 18.741446,
      "longitude": 75.297648,
      "address": "AHMEDNAGAR, Ahmednagar, Maharashtra, 413201, India",
      "area": "AHMEDNAGAR",
      "avg_review_rating": 0.0,
      "navigation_link": "https://www.google.com/maps/search/?api=1&query=18.741446,75.297648",
      "is_connected": false,
      "station_type": [
        {
          "type": "DC",
          "bg_color": "#F4F4F7",
          "text_color": "#101941"
        }
      ],
      "access_type": 1,
      "is_community_listed": false,
      "branding_logo": "https://d3orevttu06iqr.cloudfront.net/charging-pin/unavailable.png"
    }
  ],
  "ac_count": 1,
  "dc_count": 0,
  "ac_prices": [
    14.0
  ],
  "dc_prices": [],
  "scraped_at": "2026-05-21T08:01:48.281402+00:00",
  "parse_success": true,
  "missing_fields": [
    "landmark",
    "amenities_icon"
  ],
  "coverage_pct": 90.9
}