{
  "station_id": 6763,
  "station_detail": {
    "station_id": 6763,
    "station_name": "Varad Petroleum",
    "latitude": 19.691525,
    "longitude": 76.246105,
    "address": "GUT NO. 116, YADALAPUR,JALNA-MANTH RD, PO WATUR TAL-PARTUR, DISTRICT - JALNA, Jalna, Maharashtra, 431501, India",
    "area": "GUT NO. 116, YADALAPUR,JALNA-MANTH RD, PO WATUR TAL-PARTUR, DISTRICT - JALNA",
    "navigation_link": "https://www.google.com/maps/search/?api=1&query=19.691525,76.246105",
    "closing_status": {
      "text": "Open Now",
      "text_color": "#12D377"
    },
    "total_distance": "8578 kms",
    "operational_time": "24 hours",
    "connector_types": [
      {
        "id": 5,
        "connector_name": "Wall",
        "connector_image_url": "https://d3orevttu06iqr.cloudfront.net/connector_images/type-1.png"
      }
    ],
    "avg_review_rating": 0.0,
    "no_of_reviews": 0,
    "station_image_url": "https://statiq-images-prod.s3.ap-south-1.amazonaws.com/charging-stations-images/default-charging-station.jpg",
    "is_connected": false,
    "station_banner": "https://d3orevttu06iqr.cloudfront.net/banner/bpcl+banner.png",
    "landmark": null,
    "amenities_icon": [],
    "plugin_details": [
      {
        "charger_id": 54307,
        "price_with_currency": "₹ 14.0",
        "price": 14.0,
        "currency": "INR",
        "symbol": "₹",
        "connectors": [
          {
            "display_id": 1,
            "connector_id": 12452,
            "connector_type": "Wall",
            "connector_image": "https://d3orevttu06iqr.cloudfront.net/connector_images/type-1.png",
            "availability": false,
            "error_message": "Disconnected",
            "connector_type_id": 5,
            "connector_status": "faulted"
          }
        ],
        "type": "AC",
        "power_rating": 3.0,
        "charger_name": "Varad Petroleum  EC - AC",
        "last_used_on": null
      }
    ],
    "review_stats": {
      "percentage_per_star": {}
    },
    "map_pin_url": "https://statiq-images-prod.s3.ap-south-1.amazonaws.com/charging-pin/Captive.png",
    "steps_to_reach": false,
    "station_city_name": "Jalna",
    "station_access_type": "public",
    "availability": "Unavailable",
    "highest_power_rating": 3.0,
    "charger_type_of_station": "AC",
    "station_images": []
  },
  "nearby_stations": [
    {
      "id": 6763,
      "station_name": "Varad Petroleum",
      "latitude": 19.691525,
      "longitude": 76.246105,
      "address": "GUT NO. 116, YADALAPUR,JALNA-MANTH RD, PO WATUR TAL-PARTUR, DISTRICT - JALNA, Jalna, Maharashtra, 431501, India",
      "area": "GUT NO. 116, YADALAPUR,JALNA-MANTH RD, PO WATUR TAL-PARTUR, DISTRICT - JALNA",
      "avg_review_rating": 0.0,
      "navigation_link": "https://www.google.com/maps/search/?api=1&query=19.691525,76.246105",
      "is_connected": false,
      "station_type": [
        {
          "type": "AC",
          "bg_color": "#F4F4F7",
          "text_color": "#101941"
        }
      ],
      "access_type": 1,
      "is_community_listed": false,
      "branding_logo": "https://d3orevttu06iqr.cloudfront.net/charging-pin/unavailable.png"
    },
    {
      "id": 6766,
      "station_name": "Vijay Auto Services",
      "latitude": 19.650563,
      "longitude": 76.345482,
      "address": "GUT NO 127, KENDHALI SHIVAR, JALNA MANTHA ROAD , TAL- MANTHA, DISTRICT - JALNA, Jalna, Maharashtra, 431504, India",
      "area": "GUT NO 127, KENDHALI SHIVAR, JALNA MANTHA ROAD , TAL- MANTHA, DISTRICT - JALNA",
      "avg_review_rating": 0.0,
      "navigation_link": "https://www.google.com/maps/search/?api=1&query=19.650563,76.345482",
      "is_connected": false,
      "station_type": [
        {
          "type": "AC",
          "bg_color": "#F4F4F7",
          "text_color": "#101941"
        }
      ],
      "access_type": 1,
      "is_community_listed": false,
      "branding_logo": "https://d3orevttu06iqr.cloudfront.net/charging-pin/unavailable.png"
    },
    {
      "id": 7866,
      "station_name": "2012005-VAISHNAVI PETROLEUM Servotech",
      "latitude": 19.6478,
      "longitude": 76.3749,
      "address": "MANTHA, Ahmednagar, Maharashtra, 431504, India",
      "area": "MANTHA",
      "avg_review_rating": 0.0,
      "navigation_link": "https://www.google.com/maps/search/?api=1&query=19.6478,76.3749",
      "is_connected": false,
      "station_type": [
        {
          "type": "DC",
          "bg_color": "#F4F4F7",
          "text_color": "#101941"
        }
      ],
      "access_type": 1,
      "is_community_listed": false,
      "branding_logo": "https://d3orevttu06iqr.cloudfront.net/charging-pin/unavailable.png"
    },
    {
      "id": 7383,
      "station_name": "2010265-SHRI GANRAJ PETROLEUM",
      "latitude": 19.623785,
      "longitude": 76.485564,
      "address": "SELU, Selu, Maharashtra, 431509, India",
      "area": "SELU",
      "avg_review_rating": 0.0,
      "navigation_link": "https://www.google.com/maps/search/?api=1&query=19.623785,76.485564",
      "is_connected": false,
      "station_type": [
        {
          "type": "DC",
          "bg_color": "#F4F4F7",
          "text_color": "#101941"
        }
      ],
      "access_type": 1,
      "is_community_listed": false,
      "branding_logo": "https://d3orevttu06iqr.cloudfront.net/charging-pin/unavailable.png"
    },
    {
      "id": 10079,
      "station_name": "2023897-DURGESH PETROLEUM",
      "latitude": 20.00409,
      "longitude": 76.35034,
      "address": "GATE NO 66P GOVARDHAN NAGAR, Buldhana, Maharashtra, 443001, India",
      "area": "GATE NO 66P GOVARDHAN NAGAR",
      "avg_review_rating": 0.0,
      "navigation_link": "https://www.google.com/maps/search/?api=1&query=20.00409,76.35034",
      "is_connected": false,
      "station_type": [
        {
          "type": "DC",
          "bg_color": "#F4F4F7",
          "text_color": "#101941"
        }
      ],
      "access_type": 1,
      "is_community_listed": false,
      "branding_logo": "https://d3orevttu06iqr.cloudfront.net/charging-pin/unavailable.png"
    }
  ],
  "ac_count": 1,
  "dc_count": 0,
  "ac_prices": [
    14.0
  ],
  "dc_prices": [],
  "scraped_at": "2026-05-22T10:44:32.392267+00:00",
  "parse_success": true,
  "missing_fields": [
    "landmark",
    "amenities_icon"
  ],
  "coverage_pct": 90.9
}