{
  "station_id": 2123,
  "station_detail": {
    "station_id": 2123,
    "station_name": "Faction Automobiles Pvt. Ltd.",
    "latitude": 28.72842,
    "longitude": 77.04717,
    "address": "Plot No.4, Delhi, Delhi, 110081, India",
    "area": "Plot No.4",
    "navigation_link": "https://www.google.com/maps/search/?api=1&query=28.72842,77.04717",
    "closing_status": {
      "text": "Open Now",
      "text_color": "#12D377"
    },
    "total_distance": "8756 kms",
    "operational_time": "24 hours",
    "connector_types": [
      {
        "id": 3,
        "connector_name": "Type-2",
        "connector_image_url": "https://d3orevttu06iqr.cloudfront.net/connector_images/type-2.png"
      }
    ],
    "avg_review_rating": 4.0,
    "no_of_reviews": 4,
    "station_image_url": "https://statiq-images-prod.s3.ap-south-1.amazonaws.com/charging-stations-images/default-charging-station.jpg",
    "is_connected": true,
    "station_banner": "https://d3orevttu06iqr.cloudfront.net/banner/eFill+banner.png",
    "landmark": null,
    "amenities_icon": [],
    "plugin_details": [
      {
        "charger_id": 2446,
        "price_with_currency": "₹ 25.0",
        "price": 25.0,
        "currency": "INR",
        "symbol": "₹",
        "connectors": [
          {
            "display_id": 1,
            "connector_id": 3519,
            "connector_type": "Type-2",
            "connector_image": "https://d3orevttu06iqr.cloudfront.net/connector_images/type-2.png",
            "availability": true,
            "error_message": "Faulted",
            "connector_type_id": 3,
            "connector_status": "available"
          }
        ],
        "type": "AC",
        "power_rating": 7.0,
        "charger_name": "EFI Faction Automobiles Pvt. Ltd. 1",
        "last_used_on": "11/03/2025"
      }
    ],
    "review_stats": {
      "percentage_per_star": {
        "1": 25,
        "2": 0,
        "3": 0,
        "4": 0,
        "5": 75
      }
    },
    "map_pin_url": "https://statiq-images-prod.s3.ap-south-1.amazonaws.com/charging-pin/Captive.png",
    "steps_to_reach": false,
    "station_city_name": "Delhi",
    "station_access_type": "public",
    "availability": "Available",
    "highest_power_rating": 7.0,
    "charger_type_of_station": "AC",
    "station_images": []
  },
  "nearby_stations": [
    {
      "id": 2123,
      "station_name": "Faction Automobiles Pvt. Ltd.",
      "latitude": 28.72842,
      "longitude": 77.04717,
      "address": "Plot No.4, Delhi, Delhi, 110081, India",
      "area": "Plot No.4",
      "avg_review_rating": 0.0,
      "navigation_link": "https://www.google.com/maps/search/?api=1&query=28.72842,77.04717",
      "is_connected": true,
      "station_type": [
        {
          "type": "AC",
          "bg_color": "#F4F4F7",
          "text_color": "#101941"
        }
      ],
      "access_type": 1,
      "is_community_listed": false,
      "branding_logo": "https://d3orevttu06iqr.cloudfront.net/charging-pin/eFill+-+default.png"
    },
    {
      "id": 10018,
      "station_name": "Hotel Pooth Haveli & Banquets",
      "latitude": 28.7621,
      "longitude": 77.0555,
      "address": "Khasra no.154 Pooth Khurd, New Delhi, Delhi, 110039, India",
      "area": "Khasra no.154 Pooth Khurd",
      "avg_review_rating": 4.71,
      "navigation_link": "https://www.google.com/maps/search/?api=1&query=28.7621,77.0555",
      "is_connected": true,
      "station_type": [
        {
          "type": "DC",
          "bg_color": "#F4F4F7",
          "text_color": "#101941"
        }
      ],
      "access_type": 1,
      "is_community_listed": false,
      "branding_logo": "https://statiq-images-prod.s3.ap-south-1.amazonaws.com/branding_logo/statiq/statiq+pin.png"
    },
    {
      "id": 1892,
      "station_name": "Statiq DMRC Hub Nangloi Railway Station",
      "latitude": 28.682335,
      "longitude": 77.056053,
      "address": "Rohtak Road, New Delhi, Delhi, 110041, India",
      "area": "Rohtak Road",
      "avg_review_rating": 4.73,
      "navigation_link": "https://www.google.com/maps/search/?api=1&query=28.682335,77.056053",
      "is_connected": true,
      "station_type": [
        {
          "type": "DC",
          "bg_color": "#F4F4F7",
          "text_color": "#101941"
        },
        {
          "type": "AC",
          "bg_color": "#F4F4F7",
          "text_color": "#101941"
        }
      ],
      "access_type": 1,
      "is_community_listed": false,
      "branding_logo": "https://d3orevttu06iqr.cloudfront.net/branding_logo/offline-pin/unavailable+pin.png"
    },
    {
      "id": 9025,
      "station_name": "GREEN HEART FILLING STATION",
      "latitude": 28.70454,
      "longitude": 77.00105,
      "address": "New Delhi, New Delhi, Delhi, 110081, India",
      "area": "New Delhi",
      "avg_review_rating": 4.63,
      "navigation_link": "https://www.google.com/maps/search/?api=1&query=28.70454,77.00105",
      "is_connected": false,
      "station_type": [
        {
          "type": "DC",
          "bg_color": "#F4F4F7",
          "text_color": "#101941"
        }
      ],
      "access_type": 1,
      "is_community_listed": false,
      "branding_logo": "https://d3orevttu06iqr.cloudfront.net/charging-pin/unavailable.png"
    },
    {
      "id": 15883,
      "station_name": "TRIYAMJIT ENERGIES",
      "latitude": 28.77453,
      "longitude": 77.01914,
      "address": "New Delhi, New Delhi, Delhi, 110039, India",
      "area": "New Delhi",
      "avg_review_rating": 0.0,
      "navigation_link": "https://www.google.com/maps/search/?api=1&query=28.77453,77.01914",
      "is_connected": false,
      "station_type": [
        {
          "type": "DC",
          "bg_color": "#F4F4F7",
          "text_color": "#101941"
        }
      ],
      "access_type": 1,
      "is_community_listed": false,
      "branding_logo": "https://d3orevttu06iqr.cloudfront.net/charging-pin/unavailable.png"
    }
  ],
  "ac_count": 1,
  "dc_count": 0,
  "ac_prices": [
    25.0
  ],
  "dc_prices": [],
  "scraped_at": "2026-05-21T07:59:25.198825+00:00",
  "parse_success": true,
  "missing_fields": [
    "landmark",
    "amenities_icon"
  ],
  "coverage_pct": 90.9
}