{
  "station_id": 10144,
  "station_detail": {
    "station_id": 10144,
    "station_name": "2012340 - NANA PETROLEUM",
    "latitude": 20.08436,
    "longitude": 75.37984,
    "address": "GUT NO. 591, NH 752H, Aurangabad, Maharashtra, 423701, India",
    "area": "GUT NO. 591, NH 752H",
    "navigation_link": "https://www.google.com/maps/search/?api=1&query=20.08436,75.37984",
    "closing_status": {
      "text": "Open Now",
      "text_color": "#12D377"
    },
    "total_distance": "8492 kms",
    "operational_time": "24 hours",
    "connector_types": [
      {
        "id": 1,
        "connector_name": "CCS-2",
        "connector_image_url": "https://d3orevttu06iqr.cloudfront.net/connector_images/ccs-2.png"
      }
    ],
    "avg_review_rating": 3.55,
    "no_of_reviews": 38,
    "station_image_url": "https://statiq-images-prod.s3.ap-south-1.amazonaws.com/charging-stations-images/default-charging-station.jpg",
    "is_connected": true,
    "station_banner": "https://d3orevttu06iqr.cloudfront.net/banner/bpcl+banner.png",
    "landmark": null,
    "amenities_icon": [],
    "plugin_details": [
      {
        "charger_id": 59374,
        "price_with_currency": "₹ 14.0",
        "price": 14.0,
        "currency": "INR",
        "symbol": "₹",
        "connectors": [
          {
            "display_id": 1,
            "connector_id": 19996,
            "connector_type": "CCS-2",
            "connector_image": "https://d3orevttu06iqr.cloudfront.net/connector_images/ccs-2.png",
            "availability": true,
            "error_message": "Faulted",
            "connector_type_id": 1,
            "connector_status": "available"
          },
          {
            "display_id": 2,
            "connector_id": 19997,
            "connector_type": "CCS-2",
            "connector_image": "https://d3orevttu06iqr.cloudfront.net/connector_images/ccs-2.png",
            "availability": false,
            "error_message": "Charging",
            "connector_type_id": 1,
            "connector_status": "charging"
          }
        ],
        "type": "DC",
        "power_rating": 120.0,
        "charger_name": "2012340 - NANA PETROLEUM",
        "last_used_on": "20/05/2026"
      }
    ],
    "review_stats": {
      "percentage_per_star": {
        "1": 24,
        "2": 11,
        "3": 8,
        "4": 3,
        "5": 55
      }
    },
    "map_pin_url": "https://statiq-images-prod.s3.ap-south-1.amazonaws.com/charging-pin/Captive.png",
    "steps_to_reach": false,
    "station_city_name": "Aurangabad",
    "station_access_type": "public",
    "availability": "Available",
    "highest_power_rating": 120.0,
    "charger_type_of_station": "DC",
    "station_images": []
  },
  "nearby_stations": [
    {
      "id": 10144,
      "station_name": "2012340 - NANA PETROLEUM",
      "latitude": 20.08436,
      "longitude": 75.37984,
      "address": "GUT NO. 591, NH 752H, Aurangabad, Maharashtra, 423701, India",
      "area": "GUT NO. 591, NH 752H",
      "avg_review_rating": 3.55,
      "navigation_link": "https://www.google.com/maps/search/?api=1&query=20.08436,75.37984",
      "is_connected": true,
      "station_type": [
        {
          "type": "DC",
          "bg_color": "#F4F4F7",
          "text_color": "#101941"
        }
      ],
      "access_type": 1,
      "is_community_listed": false,
      "branding_logo": "https://d3orevttu06iqr.cloudfront.net/charging-pin/BPCL+-+default.png"
    },
    {
      "id": 7450,
      "station_name": "2017256-PHULAMBRI PETROLEUM",
      "latitude": 20.066586,
      "longitude": 75.405795,
      "address": "PHULAMBRI, Achalpur, Maharashtra, 431111, India",
      "area": "PHULAMBRI",
      "avg_review_rating": 4.76,
      "navigation_link": "https://www.google.com/maps/search/?api=1&query=20.066586,75.405795",
      "is_connected": false,
      "station_type": [
        {
          "type": "DC",
          "bg_color": "#F4F4F7",
          "text_color": "#101941"
        }
      ],
      "access_type": 1,
      "is_community_listed": false,
      "branding_logo": "https://d3orevttu06iqr.cloudfront.net/charging-pin/unavailable.png"
    },
    {
      "id": 13254,
      "station_name": "ID(urgxkw) M/s  Samruddhi Petroleum",
      "latitude": 20.063798,
      "longitude": 75.407149,
      "address": "Bharat Petroleum, Phulambri, Maharashtra, 431111, India",
      "area": "Bharat Petroleum",
      "avg_review_rating": 0.0,
      "navigation_link": "https://www.google.com/maps/search/?api=1&query=20.063798,75.407149",
      "is_connected": true,
      "station_type": [
        {
          "type": "DC",
          "bg_color": "#F4F4F7",
          "text_color": "#101941"
        }
      ],
      "access_type": 1,
      "is_community_listed": false,
      "branding_logo": "https://d3orevttu06iqr.cloudfront.net/charging-pin/pinGMR+default+(15).png"
    },
    {
      "id": 12714,
      "station_name": "ID(ecm532) HP AUTO CARE CENTRE HARSOOL COCO",
      "latitude": 19.913607,
      "longitude": 75.352276,
      "address": "Hudco, Aurangabad, Maharashtra, 431003, India",
      "area": "Hudco",
      "avg_review_rating": 0.0,
      "navigation_link": "https://www.google.com/maps/search/?api=1&query=19.913607,75.352276",
      "is_connected": true,
      "station_type": [
        {
          "type": "DC",
          "bg_color": "#F4F4F7",
          "text_color": "#101941"
        }
      ],
      "access_type": 1,
      "is_community_listed": false,
      "branding_logo": "https://d3orevttu06iqr.cloudfront.net/charging-pin/GMR+charging+pin-+selected.png"
    },
    {
      "id": 8490,
      "station_name": "MH | Aurangabad | Ellora Heritage Resort",
      "latitude": 20.020925,
      "longitude": 75.169883,
      "address": "Heritage Resort, Aurangabad, Maharashtra, 431102, India",
      "area": "Heritage Resort",
      "avg_review_rating": 4.52,
      "navigation_link": "https://www.google.com/maps/search/?api=1&query=20.020925,75.169883",
      "is_connected": true,
      "station_type": [
        {
          "type": "DC",
          "bg_color": "#F4F4F7",
          "text_color": "#101941"
        }
      ],
      "access_type": 1,
      "is_community_listed": false,
      "branding_logo": "https://d3orevttu06iqr.cloudfront.net/charging-pin/chargezonedefault.png"
    }
  ],
  "ac_count": 0,
  "dc_count": 1,
  "ac_prices": [],
  "dc_prices": [
    14.0
  ],
  "scraped_at": "2026-05-21T08:07:55.980198+00:00",
  "parse_success": true,
  "missing_fields": [
    "landmark",
    "amenities_icon"
  ],
  "coverage_pct": 90.9
}