{
  "station_id": 8596,
  "station_detail": {
    "station_id": 8596,
    "station_name": "M/s FRIENDS FILLING STATION",
    "latitude": 28.137904,
    "longitude": 76.654602,
    "address": "VILLAGE KATHUWAS,  ON NH08, DELHI JAIPUR ROAD,  DISTRICT - REWARI, Rewari, Haryana, 123401, India",
    "area": "VILLAGE KATHUWAS,  ON NH08, DELHI JAIPUR ROAD,  DISTRICT - REWARI",
    "navigation_link": "https://www.google.com/maps/search/?api=1&query=28.137904,76.654602",
    "closing_status": {
      "text": "Open Now",
      "text_color": "#12D377"
    },
    "total_distance": "8711 kms",
    "operational_time": "24 hours",
    "connector_types": [
      {
        "id": 1,
        "connector_name": "CCS-2",
        "connector_image_url": "https://d3orevttu06iqr.cloudfront.net/connector_images/ccs-2.png"
      }
    ],
    "avg_review_rating": 4.52,
    "no_of_reviews": 128,
    "station_image_url": "https://statiq-images-prod.s3.ap-south-1.amazonaws.com/charging-stations-images/default-charging-station.jpg",
    "is_connected": false,
    "station_banner": "https://d3orevttu06iqr.cloudfront.net/banner/bpcl+banner.png",
    "landmark": null,
    "amenities_icon": [],
    "plugin_details": [
      {
        "charger_id": 57097,
        "price_with_currency": "₹ 14.0",
        "price": 14.0,
        "currency": "INR",
        "symbol": "₹",
        "connectors": [
          {
            "display_id": 1,
            "connector_id": 16273,
            "connector_type": "CCS-2",
            "connector_image": "https://d3orevttu06iqr.cloudfront.net/connector_images/ccs-2.png",
            "availability": false,
            "error_message": "Disconnected",
            "connector_type_id": 1,
            "connector_status": "available"
          },
          {
            "display_id": 2,
            "connector_id": 16274,
            "connector_type": "CCS-2",
            "connector_image": "https://d3orevttu06iqr.cloudfront.net/connector_images/ccs-2.png",
            "availability": false,
            "error_message": "Disconnected",
            "connector_type_id": 1,
            "connector_status": "available"
          }
        ],
        "type": "DC",
        "power_rating": 120.0,
        "charger_name": "M/s FRIENDS FILLING STATION_EV_DC",
        "last_used_on": "10/05/2026"
      }
    ],
    "review_stats": {
      "percentage_per_star": {
        "1": 7,
        "2": 2,
        "3": 1,
        "4": 13,
        "5": 77
      }
    },
    "map_pin_url": "https://statiq-images-prod.s3.ap-south-1.amazonaws.com/charging-pin/Captive.png",
    "steps_to_reach": false,
    "station_city_name": "Rewari",
    "station_access_type": "public",
    "availability": "Unavailable",
    "highest_power_rating": 120.0,
    "charger_type_of_station": "DC",
    "station_images": []
  },
  "nearby_stations": [
    {
      "id": 8596,
      "station_name": "M/s FRIENDS FILLING STATION",
      "latitude": 28.137904,
      "longitude": 76.654602,
      "address": "VILLAGE KATHUWAS,  ON NH08, DELHI JAIPUR ROAD,  DISTRICT - REWARI, Rewari, Haryana, 123401, India",
      "area": "VILLAGE KATHUWAS,  ON NH08, DELHI JAIPUR ROAD,  DISTRICT - REWARI",
      "avg_review_rating": 4.52,
      "navigation_link": "https://www.google.com/maps/search/?api=1&query=28.137904,76.654602",
      "is_connected": false,
      "station_type": [
        {
          "type": "DC",
          "bg_color": "#F4F4F7",
          "text_color": "#101941"
        }
      ],
      "access_type": 1,
      "is_community_listed": false,
      "branding_logo": "https://d3orevttu06iqr.cloudfront.net/charging-pin/unavailable.png"
    },
    {
      "id": 13222,
      "station_name": "ID(6aeqpe) Bhawani sahib",
      "latitude": 28.136948,
      "longitude": 76.6537,
      "address": "Dawana, Dawana, Haryana, 123401, India",
      "area": "Dawana",
      "avg_review_rating": 0.0,
      "navigation_link": "https://www.google.com/maps/search/?api=1&query=28.136948,76.6537",
      "is_connected": true,
      "station_type": [
        {
          "type": "DC",
          "bg_color": "#F4F4F7",
          "text_color": "#101941"
        }
      ],
      "access_type": 1,
      "is_community_listed": false,
      "branding_logo": "https://d3orevttu06iqr.cloudfront.net/charging-pin/pinGMR+default+(15).png"
    },
    {
      "id": 8234,
      "station_name": "M/s KISAN FUELS",
      "latitude": 28.135718,
      "longitude": 76.650074,
      "address": "AT KASOLA,  ON DELHI JAIPUR ROAD, RHS,  DISTRICT - REWARI,, Rewari, Haryana, 123001, India",
      "area": "AT KASOLA,  ON DELHI JAIPUR ROAD, RHS,  DISTRICT - REWARI,",
      "avg_review_rating": 4.53,
      "navigation_link": "https://www.google.com/maps/search/?api=1&query=28.135718,76.650074",
      "is_connected": false,
      "station_type": [
        {
          "type": "DC",
          "bg_color": "#F4F4F7",
          "text_color": "#101941"
        }
      ],
      "access_type": 1,
      "is_community_listed": false,
      "branding_logo": "https://d3orevttu06iqr.cloudfront.net/charging-pin/unavailable.png"
    },
    {
      "id": 8600,
      "station_name": "M/s P D FILLING STATION",
      "latitude": 28.146317,
      "longitude": 76.666255,
      "address": "REWARI, Rewari, Haryana, 123401, India",
      "area": "REWARI",
      "avg_review_rating": 4.45,
      "navigation_link": "https://www.google.com/maps/search/?api=1&query=28.146317,76.666255",
      "is_connected": false,
      "station_type": [
        {
          "type": "DC",
          "bg_color": "#F4F4F7",
          "text_color": "#101941"
        }
      ],
      "access_type": 1,
      "is_community_listed": false,
      "branding_logo": "https://d3orevttu06iqr.cloudfront.net/charging-pin/unavailable.png"
    },
    {
      "id": 10747,
      "station_name": "M/s SALASAR SERVICE STATION",
      "latitude": 28.126645,
      "longitude": 76.639058,
      "address": "REWARI, Rewari, Haryana, 123401, India",
      "area": "REWARI",
      "avg_review_rating": 0.0,
      "navigation_link": "https://www.google.com/maps/search/?api=1&query=28.126645,76.639058",
      "is_connected": false,
      "station_type": [
        {
          "type": "DC",
          "bg_color": "#F4F4F7",
          "text_color": "#101941"
        }
      ],
      "access_type": 1,
      "is_community_listed": false,
      "branding_logo": "https://d3orevttu06iqr.cloudfront.net/charging-pin/unavailable.png"
    }
  ],
  "ac_count": 0,
  "dc_count": 1,
  "ac_prices": [],
  "dc_prices": [
    14.0
  ],
  "scraped_at": "2026-05-21T08:04:49.541361+00:00",
  "parse_success": true,
  "missing_fields": [
    "landmark",
    "amenities_icon"
  ],
  "coverage_pct": 90.9
}